unsub/__init__.py
unsub/applets.py
unsub/cli.py
unsub/email.py
unsub/models.py
unsub/storage.py
unsub-0.5.0.dist-info/METADATA
unsub-0.5.0.dist-info/WHEEL
unsub-0.5.0.dist-info/entry_points.txt
unsub-0.5.0.dist-info/RECORD
